thousandeyes_sdk/snapshots/__init__.py
thousandeyes_sdk/snapshots/py.typed
thousandeyes_sdk/snapshots/api/__init__.py
thousandeyes_sdk/snapshots/api/test_snapshots_api.py
thousandeyes_sdk/snapshots/models/__init__.py
thousandeyes_sdk/snapshots/models/app_and_self_links.py
thousandeyes_sdk/snapshots/models/error.py
thousandeyes_sdk/snapshots/models/link.py
thousandeyes_sdk/snapshots/models/snapshot_links.py
thousandeyes_sdk/snapshots/models/snapshot_request.py
thousandeyes_sdk/snapshots/models/snapshot_response.py
thousandeyes_sdk/snapshots/models/snapshot_test.py
thousandeyes_sdk/snapshots/models/test_interval.py
thousandeyes_sdk/snapshots/models/test_links.py
thousandeyes_sdk/snapshots/models/test_self_link.py
thousandeyes_sdk/snapshots/models/test_type.py
thousandeyes_sdk/snapshots/models/unauthorized_error.py
thousandeyes_sdk/snapshots/models/unexpanded_instant_test.py
thousandeyes_sdk/snapshots/models/unexpanded_test.py
thousandeyes_sdk/snapshots/models/validation_error.py
thousandeyes_sdk/snapshots/models/validation_error_item.py
thousandeyes_sdk_snapshots-2.23.0.dist-info/licenses/LICENSE
thousandeyes_sdk_snapshots-2.23.0.dist-info/licenses/NOTICE
thousandeyes_sdk_snapshots-2.23.0.dist-info/METADATA
thousandeyes_sdk_snapshots-2.23.0.dist-info/WHEEL
thousandeyes_sdk_snapshots-2.23.0.dist-info/top_level.txt
thousandeyes_sdk_snapshots-2.23.0.dist-info/RECORD
